runescape_wrapper/__init__.py
runescape_wrapper/osrs/__init__.py
runescape_wrapper/osrs/asyncio/__init__.py
runescape_wrapper/osrs/asyncio/exchange.py
runescape_wrapper/osrs/asyncio/hiscore.py
runescape_wrapper/osrs/asyncio/wiki.py
runescape_wrapper/osrs/sync/__init__.py
runescape_wrapper/rs3/__init__.py
runescape_wrapper/rs3/asyncio/__init__.py
runescape_wrapper/rs3/sync/__init__.py
runescape_wrapper-0.0.0.dist-info/METADATA
runescape_wrapper-0.0.0.dist-info/WHEEL
runescape_wrapper-0.0.0.dist-info/entry_points.txt
runescape_wrapper-0.0.0.dist-info/licenses/LICENSE
runescape_wrapper-0.0.0.dist-info/RECORD
